Metadata-Version: 2.1
Name: lolzmarketapi
Version: 0.2
Summary: Использование функций маркета через python
Home-page: UNKNOWN
Author-email: cotanton111@gmail.com
License: UNKNOWN
Platform: UNKNOWN
